{
  "4ac2efcbdac64f8b812c2c61cd9b9bfa": {
    "id": "4ac2efcbdac64f8b812c2c61cd9b9bfa",
    "symbol": "AAPL",
    "side": "BUY",
    "qty": 10.0,
    "type": "LIMIT",
    "limit": 190.5,
    "sl": 188.0,
    "tp": 192.0,
    "created_at": "2025-10-08T22:10:26.499765+00:00",
    "expires_at": "2025-10-08T22:10:29.499765+00:00",
    "state": "CANCELED",
    "checksum": "f194932f325319741beb14e83a9dc4ca6af8268165628ddee7ae5a69808ab416"
  },
  "b98e96a9b5d84ff3a8942c02656455f2": {
    "id": "b98e96a9b5d84ff3a8942c02656455f2",
    "symbol": "AAPL",
    "side": "BUY",
    "qty": 10.0,
    "type": "LIMIT",
    "limit": 190.5,
    "sl": 188.0,
    "tp": 192.0,
    "created_at": "2025-10-08T22:12:07.118409+00:00",
    "expires_at": "2025-10-08T22:15:07.118409+00:00",
    "state": "EXECUTED",
    "checksum": "134449f9e6ed5e913b0593a501f153223c50c186c9c5fc7810070fca7e3d103c"
  },
  "b8ebfe71cbd8496e96638e836a8778f7": {
    "id": "b8ebfe71cbd8496e96638e836a8778f7",
    "symbol": "AAPL",
    "side": "BUY",
    "qty": 10.0,
    "type": "LIMIT",
    "limit": 190.5,
    "sl": 188.0,
    "tp": 192.0,
    "created_at": "2025-10-09T19:41:14.872062+00:00",
    "expires_at": "2025-10-09T19:44:14.872062+00:00",
    "state": "REJECTED",
    "checksum": "d35d229d4c86c803214e76c1ace471cd396d503c0f72dca1f0a779289021f7d8"
  },
  "c4424d91508e495a94766462d60ce279": {
    "id": "c4424d91508e495a94766462d60ce279",
    "symbol": "SPY",
    "side": "BUY",
    "qty": 1.0,
    "type": "MARKET",
    "limit": null,
    "sl": null,
    "tp": null,
    "created_at": "2025-10-09T19:41:50.796308+00:00",
    "expires_at": "2025-10-09T19:41:53.796308+00:00",
    "state": "CANCELED",
    "checksum": "e9c60cd264ceaa0e8b8553243c9b77587940100b4e736421eb6cbaaf6099cd9d"
  },
  "cd440a74a46d44c4a6022cbd8a9d7ef3": {
    "id": "cd440a74a46d44c4a6022cbd8a9d7ef3",
    "symbol": "AAPL",
    "side": "BUY",
    "qty": 10.0,
    "type": "LIMIT",
    "limit": 190.5,
    "sl": 188.0,
    "tp": 192.0,
    "created_at": "2025-10-09T19:59:07.606868+00:00",
    "expires_at": "2025-10-09T20:02:07.606868+00:00",
    "state": "EXECUTED",
    "checksum": "06d153f153d8906b6bcd50627b573668e4ce995c107325d726227d5ab1cd41b0"
  },
  "0d72dc989d624b2dadde76c5fe9d3c6f": {
    "id": "0d72dc989d624b2dadde76c5fe9d3c6f",
    "symbol": "AAPL",
    "side": "BUY",
    "qty": 1.0,
    "type": "MARKET",
    "limit": null,
    "sl": null,
    "tp": null,
    "created_at": "2025-10-09T20:40:39.169687+00:00",
    "expires_at": "2025-10-09T20:43:39.169687+00:00",
    "state": "EXECUTED",
    "checksum": "78af7cd5dce67137ee405a602bd326a396f4a3bee69380396a7c3306894bd87a"
  },
  "488e482998224780b9e9d33713e6c599": {
    "id": "488e482998224780b9e9d33713e6c599",
    "symbol": "AAPL",
    "side": "BUY",
    "qty": 1.0,
    "type": "MARKET",
    "limit": null,
    "sl": null,
    "tp": null,
    "created_at": "2025-10-09T20:52:51.970184+00:00",
    "expires_at": "2025-10-09T20:55:51.970184+00:00",
    "state": "EXECUTED",
    "checksum": "aafe524a2c5745335cd49e7b4350b51923d53a4e9dcd4aa1c079620b2a8a546f"
  },
  "af8d1107bbd8466d828cde67ffb2a3b7": {
    "id": "af8d1107bbd8466d828cde67ffb2a3b7",
    "symbol": "AAPL",
    "side": "BUY",
    "qty": 1.0,
    "type": "MARKET",
    "limit": null,
    "sl": null,
    "tp": null,
    "created_at": "2025-10-09T20:53:17.089785+00:00",
    "expires_at": "2025-10-09T20:56:17.089785+00:00",
    "state": "EXECUTED",
    "checksum": "81c0d0d1ce5584fbeb7a01c6cfb97d8b9dd0947b421c64394379912ef2b80b76"
  },
  "4e3c4cb175e941c9b2e11c54194ef4ee": {
    "id": "4e3c4cb175e941c9b2e11c54194ef4ee",
    "symbol": "AAPL",
    "side": "BUY",
    "qty": 1.0,
    "type": "MARKET",
    "limit": null,
    "sl": null,
    "tp": null,
    "created_at": "2025-10-09T23:43:13.243901+00:00",
    "expires_at": "2025-10-09T23:45:13.243901+00:00",
    "state": "EXECUTED",
    "checksum": "b0949ad7e3d2c871fd3aadb71abf928d54028618c3011c42bba768241e74d2f4"
  },
  "41bf9c7ec82c4b19a367cccf1c187f00": {
    "id": "41bf9c7ec82c4b19a367cccf1c187f00",
    "symbol": "AAPL",
    "side": "BUY",
    "qty": 1.0,
    "type": "MARKET",
    "limit": null,
    "sl": null,
    "tp": null,
    "created_at": "2025-10-10T21:17:37.480281+00:00",
    "expires_at": "2025-10-10T21:20:37.480281+00:00",
    "state": "CONFIRMED",
    "checksum": "d0e8880328957afa4ac45577d2d6a8d309b1c6a5c8c23af50d8e37e51ebafede"
  },
  "909aedbecf4b4ebf9a46a8f755f4147a": {
    "id": "909aedbecf4b4ebf9a46a8f755f4147a",
    "symbol": "AAPL",
    "side": "BUY",
    "qty": 1.0,
    "type": "MARKET",
    "limit": null,
    "sl": null,
    "tp": null,
    "created_at": "2025-10-10T21:29:20.400860+00:00",
    "expires_at": "2025-10-10T21:32:20.400860+00:00",
    "state": "CONFIRMED",
    "checksum": "d2085a08b2a066c3c2d3e43e56e4826c319174c73f65da92dcb7c70a491cbdd5"
  },
  "1a751e5bf0024d739a8fd4307913bf84": {
    "id": "1a751e5bf0024d739a8fd4307913bf84",
    "symbol": "AAPL",
    "side": "BUY",
    "qty": 1.0,
    "type": "MARKET",
    "limit": null,
    "sl": null,
    "tp": null,
    "created_at": "2025-10-10T21:36:25.262258+00:00",
    "expires_at": "2025-10-10T21:39:25.262258+00:00",
    "state": "CONFIRMED",
    "checksum": "db0e143d072218b7bdcecad32830c209920627406ff9a6ee90681e46d25f13bd"
  },
  "81e36af943fc474fa177439e5b0f4429": {
    "id": "81e36af943fc474fa177439e5b0f4429",
    "symbol": "AAPL",
    "side": "BUY",
    "qty": 1.0,
    "type": "MARKET",
    "limit": null,
    "sl": null,
    "tp": null,
    "created_at": "2025-10-10T22:04:22.761177+00:00",
    "expires_at": "2025-10-10T22:07:22.761177+00:00",
    "state": "CONFIRMED",
    "checksum": "6ce254d1b27396d30f65555600e57031c6c9923bd798aa839e20b11890ad3adc"
  },
  "7d69a7449b0a4153a295166640575609": {
    "id": "7d69a7449b0a4153a295166640575609",
    "symbol": "AAPL",
    "side": "BUY",
    "qty": 1.0,
    "type": "MARKET",
    "limit": null,
    "sl": null,
    "tp": null,
    "created_at": "2025-10-10T22:11:57.145962+00:00",
    "expires_at": "2025-10-10T22:14:57.145962+00:00",
    "state": "CONFIRMED",
    "checksum": "03e6fd64b7142caddc02ae441c33f9676203de15618e10df2383ab1f5593e731"
  }
}